geo_gpt/__init__.py
geo_gpt/cli.py
geo_gpt/geocoder.py
geo_gpt/llm.py
geo_gpt/models.py
geo_gpt/prompts.py
geo_gpt/examples/__init__.py
geo_gpt/tests/__init__.py
geo_gpt/tests/test_geocoder.py
geo_gpt-0.1.6.dist-info/LICENSE
geo_gpt-0.1.6.dist-info/METADATA
geo_gpt-0.1.6.dist-info/WHEEL
geo_gpt-0.1.6.dist-info/entry_points.txt
geo_gpt-0.1.6.dist-info/top_level.txt
geo_gpt-0.1.6.dist-info/RECORD
