Metadata-Version: 2.2
Name: geo-gpt
Version: 0.1.6
Summary: Enhanced geocoding with pgeocode and LLM fallback
Home-page: https://github.com/zen-apps/geo-gpt
Author: Josh Janzen
Author-email: Josh Janzen <joshjanzen@gmail.com>
License: MIT
Project-URL: Homepage, https://github.com/zen-apps/geo-gpt
Project-URL: Repository, https://github.com/zen-apps/geo-gpt.git
Project-URL: Bug Tracker, https://github.com/zen-apps/geo-gpt/issues
Classifier: Development Status :: 3 - Alpha
Classifier: Intended Audience :: Developers
Classifier: Intended Audience :: Science/Research
Classifier: License :: OSI Approved :: MIT License
Classifier: Programming Language :: Python :: 3.8
Classifier: Programming Language :: Python :: 3.9
Classifier: Programming Language :: Python :: 3.10
Classifier: Programming Language :: Python :: 3.11
Classifier: Topic :: Scientific/Engineering :: GIS
Classifier: Topic :: Scientific/Engineering :: Artificial Intelligence
Requires-Python: >=3.8
License-File: LICENSE
Dynamic: author
Dynamic: home-page
Dynamic: requires-python
